<?xml version="1.0" encoding="utf-8"?>
<openerp>
    <data noupdate='0'>
    	
		<record model="audittrail.rule" id="vhr_mysite_vhr_employee_coordinate">
	    	<field name="name">VHR Mysite - Employee Coordinate</field>
	    	<field name="object_id" ref="vhr_mysite.model_vhr_employee_coordinate"/>
			<field name="user_id" search="[]"/>
			<field name="log_read" eval="False"/>
			<field name="log_create" eval="True"/>
			<field name="log_write" eval="True"/>
			<field name="log_unlink" eval="True"/>
			<field name="log_action" eval="False"/>
			<field name="log_workflow" eval="False"/>
            <field name="state">subscribed</field>
        </record>
        
        <record model="audittrail.rule" id="vhr_mysite_vhr_mysite_benefit_salary">
	    	<field name="name">VHR Mysite - Benefit Salary</field>
	    	<field name="object_id" ref="vhr_mysite.model_vhr_mysite_benefit_salary"/>
			<field name="user_id" search="[]"/>
			<field name="log_read" eval="False"/>
			<field name="log_create" eval="True"/>
			<field name="log_write" eval="True"/>
			<field name="log_unlink" eval="True"/>
			<field name="log_action" eval="False"/>
			<field name="log_workflow" eval="False"/>
            <field name="state">subscribed</field>
        </record>
	    
        
    </data>
</openerp>

