<?xml version="1.0" encoding="UTF-8"?>
<openerp>
	<data noupdate='1'>
		<record id="hrs_data_privacy_statement_01" model="vhr.dimension">
			<field name="name">Letter Salary Increase</field>
			<field name="description">Increase</field>
			<field name="dimension_type_id" eval="ref('vhr_human_resource.data_dimension_type_PRIVACY_STATEMENT_REPORT')"/>
			<field name="code">letter_salary_increase</field>
			<field name="active">true</field>
		</record>
		
		<record id="hrs_data_privacy_statement_02" model="vhr.dimension">
			<field name="name">Letter Salary Freeze</field>
			<field name="description">Freeze</field>
			<field name="dimension_type_id" eval="ref('vhr_human_resource.data_dimension_type_PRIVACY_STATEMENT_REPORT')"/>
			<field name="code">letter_salary_freeze</field>
			<field name="active">true</field>
		</record>
		
		<record id="hrs_data_privacy_statement_03" model="vhr.dimension">
			<field name="name">Letter Salary Decrease</field>
			<field name="description">Decrease</field>
			<field name="dimension_type_id" eval="ref('vhr_human_resource.data_dimension_type_PRIVACY_STATEMENT_REPORT')"/>
			<field name="code">letter_salary_decrease</field>
			<field name="active">true</field>
		</record>
		
		<record id="hrs_data_privacy_statement_04" model="vhr.dimension">
			<field name="name">Letter Promotion</field>
			<field name="description">Promotion</field>
			<field name="dimension_type_id" eval="ref('vhr_human_resource.data_dimension_type_PRIVACY_STATEMENT_REPORT')"/>
			<field name="code">letter_promotion</field>
			<field name="active">true</field>
		</record>
		
		<record id="vhr_dimension_career_track_01" model="vhr.dimension">
			<field name="name">Management</field>
			<field name="description">Management</field>
			<field name="dimension_type_id" eval="ref('vhr_human_resource.data_dimension_type_CAREER_TRACK')"/>
			<field name="code">Management</field>
			<field name="active">true</field>
		</record>
		
		<record id="vhr_dimension_career_track_02" model="vhr.dimension">
			<field name="name">Professional</field>
			<field name="description">Professional</field>
			<field name="dimension_type_id" eval="ref('vhr_human_resource.data_dimension_type_CAREER_TRACK')"/>
			<field name="code">Professional</field>
			<field name="active">true</field>
		</record>
		
		<record id="vhr_dimension_career_track_03" model="vhr.dimension">
			<field name="name">Para-Professional</field>
			<field name="description">Para-Professional</field>
			<field name="dimension_type_id" eval="ref('vhr_human_resource.data_dimension_type_CAREER_TRACK')"/>
			<field name="code">P-Professional</field>
			<field name="active">true</field>
		</record>
		
		
		<record id="vhr_dimension_multi_renew_contract_type_of_person_01" model="vhr.dimension">
			<field name="name">Team Leader</field>
			<field name="description">Team Leader</field>
			<field name="dimension_type_id" eval="ref('vhr_human_resource.data_dimension_type_multi_renew_contract_type_of_person')"/>
			<field name="code">team_leader</field>
			<field name="active">true</field>
		</record>
		
		<record id="vhr_dimension_multi_renew_contract_type_of_person_02" model="vhr.dimension">
			<field name="name">Dept Head</field>
			<field name="description">Dept Head</field>
			<field name="dimension_type_id" eval="ref('vhr_human_resource.data_dimension_type_multi_renew_contract_type_of_person')"/>
			<field name="code">dept_head</field>
			<field name="active">true</field>
		</record>
		
		<record id="vhr_dimension_multi_renew_contract_type_of_person_03" model="vhr.dimension">
			<field name="name">HRBP</field>
			<field name="description">HRBP</field>
			<field name="dimension_type_id" eval="ref('vhr_human_resource.data_dimension_type_multi_renew_contract_type_of_person')"/>
			<field name="code">hrbp</field>
			<field name="active">true</field>
		</record>
		
		<record id="vhr_dimension_multi_renew_contract_type_of_person_04" model="vhr.dimension">
			<field name="name">Direct Boss</field>
			<field name="description">Direct Boss</field>
			<field name="dimension_type_id" eval="ref('vhr_human_resource.data_dimension_type_multi_renew_contract_type_of_person')"/>
			<field name="code">direct_boss</field>
			<field name="active">true</field>
		</record>
		
		<record id="vhr_dimension_multi_renew_contract_type_of_person_05" model="vhr.dimension">
			<field name="name">Assistant HRBP</field>
			<field name="description">Assistant HRBP</field>
			<field name="dimension_type_id" eval="ref('vhr_human_resource.data_dimension_type_multi_renew_contract_type_of_person')"/>
			<field name="code">ass_hrbp</field>
			<field name="active">true</field>
		</record>
		
		<record id="vhr_dimension_type_of_extend_appendix_contract_1_year" model="vhr.dimension">
			<field name="name">Phụ lục hợp đồng 1 năm</field>
			<field name="description">Phụ lục hợp đồng 1 năm</field>
			<field name="dimension_type_id" eval="ref('vhr_human_resource.data_dimension_type_of_extend_appendix_contract')"/>
			<field name="code">appendix_1_year</field>
			<field name="active">true</field>
		</record>
		
		<record id="vhr_dimension_type_of_extend_appendix_contract_2_year" model="vhr.dimension">
			<field name="name">Phụ lục hợp đồng 2 năm</field>
			<field name="description">Phụ lục hợp đồng 2 năm</field>
			<field name="dimension_type_id" eval="ref('vhr_human_resource.data_dimension_type_of_extend_appendix_contract')"/>
			<field name="code">appendix_2_year</field>
			<field name="active">true</field>
		</record>
		
		
	</data>
</openerp>